silent_tools.py
_helpers_silent/rosetta_util.py
silent_tools-1.0.1.data/scripts/_extract_flags.sh
silent_tools-1.0.1.data/scripts/pyextract_pdbs
silent_tools-1.0.1.data/scripts/pyjd2
silent_tools-1.0.1.data/scripts/silentassertuniquetags
silent_tools-1.0.1.data/scripts/silentclearscores
silent_tools-1.0.1.data/scripts/silentdd
silent_tools-1.0.1.data/scripts/silentdropcorruptmodels
silent_tools-1.0.1.data/scripts/silentdropduplicatesequences
silent_tools-1.0.1.data/scripts/silentdropduplicatesequencesch1
silent_tools-1.0.1.data/scripts/silentextract
silent_tools-1.0.1.data/scripts/silentextractlig
silent_tools-1.0.1.data/scripts/silentextractparallel
silent_tools-1.0.1.data/scripts/silentextractspecific
silent_tools-1.0.1.data/scripts/silentfasterslice
silent_tools-1.0.1.data/scripts/silentfastslice
silent_tools-1.0.1.data/scripts/silentfrompdbs
silent_tools-1.0.1.data/scripts/silentfrompdbsparallel
silent_tools-1.0.1.data/scripts/silentgreppdbinfolabels
silent_tools-1.0.1.data/scripts/silentinjectscores
silent_tools-1.0.1.data/scripts/silentls
silent_tools-1.0.1.data/scripts/silentmultislice
silent_tools-1.0.1.data/scripts/silentoopsdropcorruptmodels
silent_tools-1.0.1.data/scripts/silentoopsdropcorruptmodelsrename
silent_tools-1.0.1.data/scripts/silentoopsscoreslice
silent_tools-1.0.1.data/scripts/silentoopsslice
silent_tools-1.0.1.data/scripts/silentorigls
silent_tools-1.0.1.data/scripts/silentrename
silent_tools-1.0.1.data/scripts/silentscorefile
silent_tools-1.0.1.data/scripts/silentsequence
silent_tools-1.0.1.data/scripts/silentsketchextract
silent_tools-1.0.1.data/scripts/silentsketchextractca
silent_tools-1.0.1.data/scripts/silentsketchextractcaprotein
silent_tools-1.0.1.data/scripts/silentsketchextractch1
silent_tools-1.0.1.data/scripts/silentsketchextractspecific
silent_tools-1.0.1.data/scripts/silentsketchfrompdbs
silent_tools-1.0.1.data/scripts/silentslice
silent_tools-1.0.1.data/scripts/silentsplit
silent_tools-1.0.1.data/scripts/silentsplitaf3buckets
silent_tools-1.0.1.dist-info/LICENSE
silent_tools-1.0.1.dist-info/METADATA
silent_tools-1.0.1.dist-info/WHEEL
silent_tools-1.0.1.dist-info/top_level.txt
silent_tools-1.0.1.dist-info/RECORD
