Metadata-Version: 2.1
Name: silent-tools
Version: 1.0.1
Summary: A bunch of shell utilities for dealing with silent files
Home-page: https://github.com/bcov77/silent_tools
Author: Brian Coventry
Author-email: bcoventry77@gmail.com
License: MIT
Download-URL: https://github.com/bcov77/silent_tools/archive/refs/tags/v1.0.1.tar.gz
Platform: UNKNOWN
License-File: LICENSE
Requires-Dist: numpy
